LICENSE
pixelfuse/__init__.py
pixelfuse/__main__.py
pixelfuse/cli.py
pixelfuse/src/f2lfv.py
pixelfuse/src/f2v.py
pixelfuse/src/lfv2f.py
pixelfuse/src/v2f.py
pixelfuse-3.0.0.dist-info/LICENSE
pixelfuse-3.0.0.dist-info/METADATA
pixelfuse-3.0.0.dist-info/WHEEL
pixelfuse-3.0.0.dist-info/RECORD
